py_nacos_client/__init__.py
py_nacos_client/adapter_server.py
py_nacos_client/clienterror.py
py_nacos_client/logger.py
py_nacos_client/microservice.yaml
py_nacos_client/nacos_client.py
py_nacos_client/nacos_config.ini
py_nacos_client/utils.py
py_nacos_client-0.1.7.dist-info/LICENSE
py_nacos_client-0.1.7.dist-info/METADATA
py_nacos_client-0.1.7.dist-info/WHEEL
py_nacos_client-0.1.7.dist-info/top_level.txt
py_nacos_client-0.1.7.dist-info/RECORD
