Metadata-Version: 2.1
Name: py-nacos-client
Version: 0.1.7
Summary: Python client for Nacos.
Home-page: UNKNOWN
Author: lijiarui
License: UNKNOWN
Keywords: jd_nacos_py
Platform: UNKNOWN
Classifier: Operating System :: OS Independent
Classifier: Intended Audience :: Developers
Classifier: License :: OSI Approved :: MIT License
Requires-Python: >=3
License-File: LICENSE
Requires-Dist: nacos-sdk-python
